sdmc_tools/__init__.py
sdmc_tools/constants.py
sdmc_tools/data_dictionary_TEMPLATE.xlsx
sdmc_tools/data_dictionary_nonstandard_vars.xlsx
sdmc_tools/deprecated_generate_README.py
sdmc_tools/generate_README.py
sdmc_tools/generate_dict.py
sdmc_tools/lut_table.txt
sdmc_tools/process.py
sdmc_tools/readme_template.md
sdmc_tools/regenerate_README.py
sdmc_tools-0.0.2.dist-info/LICENSE
sdmc_tools-0.0.2.dist-info/METADATA
sdmc_tools-0.0.2.dist-info/WHEEL
sdmc_tools-0.0.2.dist-info/entry_points.txt
sdmc_tools-0.0.2.dist-info/top_level.txt
sdmc_tools-0.0.2.dist-info/RECORD
